LICENSE
MANIFEST.in
README.md
requirements.txt
setup.py
getm/__init__.py
getm/checksum.py
getm/cli.py
getm/http.py
getm/progress.py
getm/reader.py
getm/utils.py
getm/version.py
getm.egg-info/PKG-INFO
getm.egg-info/SOURCES.txt
getm.egg-info/dependency_links.txt
getm.egg-info/entry_points.txt
getm.egg-info/not-zip-safe
getm.egg-info/requires.txt
getm.egg-info/top_level.txt
getm/concurrent/__init__.py
getm/concurrent/buffers.py
getm/concurrent/collections.py
getm/concurrent/shared_memory_37/__init__.py
getm/concurrent/shared_memory_37/shared_memory.py
getm/concurrent/shared_memory_37/clinic/posixshmem.c.h
tests/test_checksum.py
tests/test_cli.py
tests/test_concurrent_buffers.py
tests/test_concurrent_collections.py
tests/test_getm.py
tests/test_http.py
tests/test_progress.py
tests/test_reader.py
tests/test_utils.py
tests/infra/__init__.py
tests/infra/profile.py
tests/infra/server.py