Metadata-Version: 2.1
Name: getm
Version: 0.0.5
Summary: Download data from URLs quickly, with integrity
Home-page: https://github.com/DataBiosphere/getm.git
Author: Brian Hannafious
Author-email: bhannafi@ucsc.edu
License: MIT
Platform: MacOS X
Platform: Posix
Classifier: Intended Audience :: Developers
Classifier: License :: OSI Approved :: MIT License
Classifier: Programming Language :: Python :: 3.7
Requires-Python: >=3.7.7
License-File: LICENSE
